RTL/data_mem.sv
module data_mem (
    input wire clk,
    input wire rst,
    input wire [31:0] addr,
    input wire [31:0] din,
    input wire [3:0] we,
    output reg [31:0] dout
);

    reg [31:0] mem [0:255]; // 256-word data memory

    always @(posedge clk) begin
        if (rst) begin
            for (int i = 0; i < 256; i = i + 1) begin
                mem[i] <= 0;
            end
        end else begin
            if (we[0]) mem[addr[9:2]][7:0]   <= din[7:0];
            if (we[1]) mem[addr[9:2]][15:8]  <= din[15:8];
            if (we[2]) mem[addr[9:2]][23:16] <= din[23:16];
            if (we[3]) mem[addr[9:2]][31:24] <= din[31:24];
            dout <= mem[addr[9:2]]; // Word-aligned access
        end
    end
endmodule // data_mem

RTL/alu.sv
module alu (
		input wire clk,
		input wire rst,
		input wire [31:0] a,
		input wire [31:0] b,
		input wire [3:0] op,
		output reg [31:0] result
		);

   always @(posedge clk) begin
      if (rst)
	  	result <= 0;
      else
		case (op)
			4'b0000:	result <= a + b; // ADD
			4'b0001:	result <= a - b; // SUB
			4'b0010:	result <= a & b; // AND
			4'b0011:	result <= a | b; // OR
			4'b0100:	result <= a ^ b; // XOR
			default:	result <= 0;
		endcase
   end
endmodule // alu

RTL/control_unit.v
module control_unit (
    input wire clk,
    input wire rst,
    input wire [6:0] op,
    input wire [2:0] funct3,
    input wire [6:0] funct7,
    input wire zero;

    output reg pc_src,
    output reg ResultSrc,
    output reg MemWrite,
    output reg [2:0] ALUControl;
    output reg ALUSrc,
    output reg [1:0] ImmSrc,
    output reg RegWrite,
    
);
    always @(posedge clk) begin
        if (rst) begin
            alu_op <= 0;
            pc <= 0;
        end else begin
            case (instr[31:26]) // opcode
                6'b000000: begin // R-type
                case (instr[5:0]) // funct
                    6'b100000: alu_op <= 4'b0000; // ADD
                    6'b100010: alu_op <= 4'b0001; // SUB
                    6'b100100: alu_op <= 4'b0010; // AND
                    6'b100101: alu_op <= 4'b0011; // OR
                    6'b100110: alu_op <= 4'b0100; // XOR
                    default:   alu_op <= 0;
                endcase
                end
                default: alu_op <= 0;
            endcase
            pc <= pc + 4; // Increment PC by 4 for next instruction
        end
    end
    
endmodule

RTL/cpu_top.v
module cpu_top (
    input wire clk,
    input wire rst,
    input wire [31:0] instr,
    output reg [31:0] pc
);

    wire [3:0] alu_op;
    wire [31:0] alu_result;
    wire [31:0] data_out;

    control_unit cu (
        .clk(clk),
        .rst(rst),
        .instr(instr),
        .alu_op(alu_op),
        .pc(pc)
    );

    alu alu (
        .clk(clk),
        .rst(rst),
        .a(32'h00000000), // Placeholder for register value
        .b(32'h00000000), // Placeholder for register value
        .op(alu_op),
        .result(alu_result)
    );

    data_mem dm (
        .clk(clk),
        .rst(rst),
        .addr(alu_result), // Address from ALU result
        .din(32'h00000000), // Placeholder for data to write
        .we(4'b0000), // Placeholder for write enable
        .dout(data_out)
    );
endmodule

SIMULATION/simx.vcd
$version Generated by VerilatedVcd $end
$timescale 1ps $end
 $scope module TOP $end
  $var wire 1 ' clk $end
  $var wire 1 ( rst $end
  $var wire 32 ) instr [31:0] $end
  $var wire 32 * pc [31:0] $end
  $scope module cpu_top $end
   $var wire 1 ' clk $end
   $var wire 1 ( rst $end
   $var wire 32 ) instr [31:0] $end
   $var wire 32 * pc [31:0] $end
   $var wire 4 # alu_op [3:0] $end
   $var wire 32 $ alu_result [31:0] $end
   $var wire 32 % data_out [31:0] $end
   $scope module alu $end
    $var wire 1 ' clk $end
    $var wire 1 ( rst $end
    $var wire 32 + a [31:0] $end
    $var wire 32 + b [31:0] $end
    $var wire 4 # op [3:0] $end
    $var wire 32 $ result [31:0] $end
   $upscope $end
   $scope module cu $end
    $var wire 1 ' clk $end
    $var wire 1 ( rst $end
    $var wire 32 ) instr [31:0] $end
    $var wire 4 # alu_op [3:0] $end
    $var wire 32 * pc [31:0] $end
   $upscope $end
   $scope module dm $end
    $var wire 1 ' clk $end
    $var wire 1 ( rst $end
    $var wire 32 $ addr [31:0] $end
    $var wire 32 + din [31:0] $end
    $var wire 4 , we [3:0] $end
    $var wire 32 % dout [31:0] $end
    $scope module unnamedblk1 $end
     $var wire 32 & i [31:0] $end
    $upscope $end
   $upscope $end
  $upscope $end
 $upscope $end
$enddefinitions $end


#0
b0000 #
b00000000000000000000000000000000 $
b00000000000000000000000000000000 %
b00000000000000000000000000000000 &
1'
1(
b00000000000000000000000000100000 )
b00000000000000000000000000000000 *
b00000000000000000000000000000000 +
b0000 ,
#5
0'
#10
b00000000000000000000000100000000 &
1'
#15
0'
#20
1'
0(
b00000000000000000000000000000100 *
#25
0'
#30
1'
b00000000000000000000000000001000 *
#35
0'
#40
b0001 #
1'
b00000000000000000000000000100010 )
b00000000000000000000000000001100 *
#45
0'
#50
1'
b00000000000000000000000000010000 *
#55
0'
#60
b0010 #
1'
b00000000000000000000000000100100 )
b00000000000000000000000000010100 *
#65
0'
#70
1'
b00000000000000000000000000011000 *
#75
0'
#80
b0011 #
1'
b00000000000000000000000000100101 )
b00000000000000000000000000011100 *
#85
0'
#90
1'
b00000000000000000000000000100000 *
#95
0'
#100
b0100 #
1'
b00000000000000000000000000100110 )
b00000000000000000000000000100100 *
#105
0'
#110
1'
b00000000000000000000000000101000 *
#115
0'
#120
1'
b00000000000000000000000000101100 *
#125
0'
#130
1'
b00000000000000000000000000110000 *
